{
  "posts": [
    {
      "id": 1,
      "name": "Table",
      "description": "Wood Table",
      "category": "wood Furniture",
      "price": "700",
      "quantity": "9",
      "supplier": "Jhon Wood"
    },
    {
      "id": 2,
      "name": "Ruan Carlos Passeto",
      "description": "Wood Table",
      "category": "wood Furniture",
      "price": "5",
      "quantity": "5",
      "supplier": "Jhon Wood"
    },
    {
      "id": 3,
      "name": "Table",
      "description": "glassTable",
      "category": "glass",
      "price": "500",
      "quantity": "8",
      "supplier": "Jhon Wood"
    },
    {
      "id": 4,
      "name": "meudb",
      "description": "Wood Table",
      "category": "wood Furniture",
      "price": "500",
      "quantity": "8",
      "supplier": "Jhon Wood"
    }
  ]
}